{"api_core.md":"CWOgPaLf","changelog.md":"BZowRhF5","components_base_badge.md":"BQPC4YWo","components_base_button.md":"Ct2SFaAy","components_base_divider.md":"DVLt-vfr","components_base_icon.md":"DzrI4UQa","components_base_space.md":"CQg4_tiA","components_business_markdown-editor.md":"De6bNlDA","components_business_pro-table.md":"CvKb4k1Y","components_business_search-form.md":"56G3rfnZ","components_business_statistic.md":"ZjmLV1H_","components_data_avatar.md":"twgqJkbt","components_data_card.md":"nGXPv-DF","components_data_carousel.md":"Ctl9wz4i","components_data_descriptions.md":"DMF8oPeN","components_data_dynamic-table.md":"6PsZ2UyP","components_data_empty.md":"CozXojf-","components_data_pagination.md":"Cy0a0ETZ","components_data_progress.md":"Bt0oyDRN","components_data_scrollbar.md":"XKWkRRkr","components_data_table.md":"xqKckEsQ","components_data_tag.md":"COmAhB3G","components_data_timeline.md":"CFlT3gxI","components_data_tree.md":"Bb2d20B7","components_feedback_alert.md":"CtQjge-v","components_feedback_backtop.md":"DCnHNN2-","components_feedback_drawer.md":"D1NbXW4a","components_feedback_message-box.md":"vk1JpRZB","components_feedback_message.md":"BzzDYRzQ","components_feedback_modal.md":"He841fCR","components_feedback_notification.md":"SXyVnzSI","components_feedback_popconfirm.md":"_uu48UZ0","components_feedback_tooltip.md":"DvIeK1AU","components_form_checkbox.md":"6Wc0kgKV","components_form_date-picker.md":"CQq1XQ60","components_form_form.md":"7cqYFPhr","components_form_input-number.md":"mFZlnaz6","components_form_input.md":"BGHz6qh2","components_form_radio.md":"QOViiszT","components_form_rate.md":"BnPhvR4X","components_form_select.md":"Cn3GQ5gl","components_form_slider.md":"Dopq4kVr","components_form_switch.md":"Fj6sYbpC","components_form_textarea.md":"CDCZmKKZ","components_form_time-picker.md":"BFsUER72","components_form_transfer.md":"D8sEsZGU","components_form_upload.md":"Dv1PoRMR","components_layout_container.md":"DN9wyO4x","components_layout_grid.md":"BCcWwxes","components_navigation_breadcrumb.md":"CosuB6uu","components_navigation_dropdown.md":"5TYRyI_T","components_navigation_menu.md":"JvWaQtIR","components_navigation_page-header.md":"CBiioMlA","components_navigation_steps.md":"DdcRID2B","components_navigation_tabs.md":"x1kAQz9z","guide_getting-started.md":"DcbryYDv","guide_installation.md":"Di_fWk2_","guide_quick-start.md":"iOk_Q-si","guide_releasing.md":"CWn5l3Ir","guide_theming.md":"8qiIW_pf","index.md":"DOATmW1d"}
